[
  { "id": 1, "ja": "彼は自分が無実であることをはっきりさせた。", "en": "He made it clear that he is innocent." },
  { "id": 2, "ja": "彼女が来なかったのは奇妙だと感じた。", "en": "I found it strange that she didn't come." },
  { "id": 3, "ja": "彼が冗談を言っているのは明らかだった。", "en": "He made it obvious that he was joking." },
  { "id": 4, "ja": "彼らが勝つ可能性が高いと思っている。", "en": "I think it likely that they will win." },
  { "id": 5, "ja": "彼女は興味がないことをはっきりと示した。", "en": "She made it clear that she was not interested." },
  { "id": 6, "ja": "全員が目標を理解することが重要だと考えている。", "en": "We consider it important that everyone understands the goal." },
  { "id": 7, "ja": "彼がこれほど冷静なのは驚きだった。", "en": "I found it surprising that he was so calm." },
  { "id": 8, "ja": "彼らは助けたいという意思をはっきりさせた。", "en": "They made it clear that they wanted to help." },
  { "id": 9, "ja": "今これについて議論する必要があると感じている。", "en": "I feel it necessary that we discuss this now." },
  { "id": 10, "ja": "彼がミスをしたことは明白だった。", "en": "He made it evident that he had made a mistake." },
  { "id": 11, "ja": "彼がその歌を気に入っているのは興味深い。", "en": "I find it interesting that he likes that song." },
  { "id": 12, "ja": "彼らが迷子になった可能性があると考えた。", "en": "We thought it possible that they were lost." },
  { "id": 13, "ja": "彼女は去ることをはっきりと伝えた。", "en": "She made it plain that she was leaving." },
  { "id": 14, "ja": "時間通りに終わらせることが不可欠だと考えている。", "en": "I consider it essential that you finish on time." },
  { "id": 15, "ja": "彼が忙しいということをはっきりさせた。", "en": "He made it clear that he was busy." },
  { "id": 16, "ja": "誰も一言も話さなかったのは奇妙だと思った。", "en": "I found it odd that nobody said a word." },
  { "id": 17, "ja": "彼らが不満を持っていることが明らかになった。", "en": "They made it apparent that they were unhappy." },
  { "id": 18, "ja": "彼がその仕事に就くことが重要だと信じている。", "en": "I believe it important that he gets the job." },
  { "id": 19, "ja": "彼女が来ないことを明確にした。", "en": "She made it clear that she wasn't coming." },
  { "id": 20, "ja": "待たなければならないのは残念だと感じている。", "en": "I find it unfortunate that we have to wait." }
]