[
  { "id": 1, "ja": "彼女がバスを待っているのを見た。", "en": "I saw her waiting for the bus." },
  { "id": 2, "ja": "電話が鳴っているのが聞こえた。", "en": "I heard the phone ringing." },
  { "id": 3, "ja": "彼らがサッカーをしているのを見ていた。", "en": "I watched the team playing soccer." },
  { "id": 4, "ja": "地面が揺れているのを感じた。", "en": "I felt the ground shaking." },
  { "id": 5, "ja": "彼がこっそり出て行くのに気づいた。", "en": "I noticed him sneaking out." },
  { "id": 6, "ja": "台所で何かが焦げている匂いがした。", "en": "I smelled something burning in the kitchen." },
  { "id": 7, "ja": "彼がお金を盗んでいるところを見つけた。", "en": "I caught him stealing money." },
  { "id": 8, "ja": "雨が窓を叩いている音を聞いていた。", "en": "I listened to the rain hitting the window." },
  { "id": 9, "ja": "鳥が雛に餌をやっているのを観察した。", "en": "I observed the bird feeding its chicks." },
  { "id": 10, "ja": "心臓が激しく動いているのを感じた。", "en": "I felt my heart racing." },
  { "id": 11, "ja": "子供たちが走り回っているのを見た。", "en": "I saw the kids running around." },
  { "id": 12, "ja": "誰かが私の名前を呼んでいるのが聞こえた。", "en": "I heard someone calling my name." },
  { "id": 13, "ja": "雲がゆっくり流れていくのを眺めていた。", "en": "I watched the clouds drifting by." },
  { "id": 14, "ja": "雪が静かに降っているのに気づいた。", "en": "I noticed the snow falling silently." },
  { "id": 15, "ja": "パンが焼けている美味しそうな匂いがした。", "en": "I smelled the bread baking." },
  { "id": 16, "ja": "彼らがひそひそ話しているのを聞きつけた。", "en": "I caught them whispering." },
  { "id": 17, "ja": "近くで犬が吠えているのが聞こえた。", "en": "I heard a dog barking nearby." },
  { "id": 18, "ja": "車がこちらへ向かってくるのを見た。", "en": "I saw the car coming." },
  { "id": 19, "ja": "星が夜空で瞬いているのを眺めていた。", "en": "I observed the stars twinkling in the sky." },
  { "id": 20, "ja": "シェフが料理を準備しているのを見ていた。", "en": "I watched the chef preparing the food." }
]